{
  "about": {
    "試合日": "2014年05月05日 第5試合目",
    "グランド": "",
    "先攻バッテリー": "",
    "後攻バッテリー": "本田、有山、藤原",
    "長打": "(三)藤原 《安打数：5本》",
    "内容": ""
  },
  "scores": [
    {
      "team": "広研モザイク",
      "totalPoint": "2",
      "pointHistory": [
        "0",
        "1",
        "1",
        "0",
        "0",
        "0",
        "0"
      ]
    },
    {
      "team": "大阪フライヤーズ",
      "totalPoint": "11",
      "pointHistory": [
        "3",
        "0",
        "0",
        "1",
        "1",
        "6",
        "X"
      ]
    }
  ],
  "batter": [
    {
      "order": "1",
      "pos": "左翼手",
      "name": "前田(5)",
      "history": [
        "中安",
        "",
        "三安",
        "三振",
        "",
        "三失",
        "",
        "",
        "",
        "",
        "",
        ""
      ],
      "打点": "0",
      "盗塁": "1",
      "盗失": "1",
      "得点": "3",
      "失策": "0",
      "美技": "0"
    },
    {
      "order": "2",
      "pos": "捕手",
      "name": "伊木(18)",
      "history": [
        "四球",
        "",
        "三ゴ",
        "",
        "四球",
        "四球",
        "",
        "",
        "",
        "",
        "",
        ""
      ],
      "打点": "0",
      "盗塁": "1",
      "盗失": "0",
      "得点": "2",
      "失策": "0",
      "美技": "0"
    },
    {
      "order": "3",
      "pos": "一塁手",
      "name": "有山(45)",
      "history": [
        "三ゴ",
        "",
        "三振",
        "",
        "投飛",
        "死球",
        "",
        "",
        "",
        "",
        "",
        ""
      ],
      "打点": "0",
      "盗塁": "0",
      "盗失": "0",
      "得点": "1",
      "失策": "3",
      "美技": "0"
    },
    {
      "order": "4",
      "pos": "二塁手",
      "name": "藤田(41)",
      "history": [
        "四球",
        "",
        "",
        "投安",
        "四球",
        "四球①",
        "",
        "",
        "",
        "",
        "",
        ""
      ],
      "打点": "1",
      "盗塁": "1",
      "盗失": "0",
      "得点": "3",
      "失策": "0",
      "美技": "0"
    },
    {
      "order": "5",
      "pos": "右翼手",
      "name": "片田(51)",
      "history": [
        "三振",
        "",
        "",
        "四球",
        "一ゴ",
        "遊ゴ",
        "",
        "",
        "",
        "",
        "",
        ""
      ],
      "打点": "0",
      "盗塁": "0",
      "盗失": "0",
      "得点": "0",
      "失策": "0",
      "美技": "0"
    },
    {
      "order": "6",
      "pos": "三塁手",
      "name": "藤原(8)",
      "history": [
        "中3①",
        "",
        "",
        "中直",
        "",
        "四球",
        "二安②",
        "",
        "",
        "",
        "",
        ""
      ],
      "打点": "3",
      "盗塁": "0",
      "盗失": "0",
      "得点": "1",
      "失策": "0",
      "美技": "0"
    },
    {
      "order": "7",
      "pos": "遊撃手",
      "name": "古川(32)",
      "history": [
        "",
        "遊ゴ",
        "",
        "四球",
        "",
        "四球",
        "左飛",
        "",
        "",
        "",
        "",
        ""
      ],
      "打点": "0",
      "盗塁": "0",
      "盗失": "0",
      "得点": "1",
      "失策": "0",
      "美技": "0"
    },
    {
      "order": "8",
      "pos": "投手",
      "name": "本田(3)",
      "history": [
        "",
        "遊ゴ",
        "",
        "死球①",
        "",
        "三振",
        "",
        "",
        "",
        "",
        "",
        ""
      ],
      "打点": "1",
      "盗塁": "0",
      "盗失": "0",
      "得点": "0",
      "失策": "0",
      "美技": "0"
    }
  ],
  "pitcher": [
    {
      "name": "本田(3)",
      "イニング数": "4回",
      "自責点": "",
      "失点": "2",
      "三振": "",
      "四球": "6",
      "死球": "",
      "被安": "3",
      "被本": "",
      "投球数": "",
      "暴投": "",
      "勝敗": "勝"
    },
    {
      "name": "藤原(8)",
      "イニング数": "1回",
      "自責点": "",
      "失点": "",
      "三振": "1",
      "四球": "1",
      "死球": "",
      "被安": "",
      "被本": "",
      "投球数": "",
      "暴投": "",
      "勝敗": "-"
    }
  ]
}