{
  "about": {
    "試合日": "2018年11月24日 第1試合目",
    "グランド": "寺田町野球場",
    "先攻バッテリー": "渡辺・本田・河合－細野・大野",
    "後攻バッテリー": "",
    "長打": "(二)渡辺 本田 河合 平嶋 大野 《安打数：15本》",
    "内容": "スカイカップ トーナメント準々決勝\n大阪フライヤーズ 13-0 大阪ヤンキース\n毎回得点、ほぼ先発全員打点、ほぼ先発全員得点\n渡辺→本田→河合リレーで無四球完封\n文句なしの試合運びで快勝。"
  },
  "scores": [
    {
      "team": "大阪フライヤーズ",
      "totalPoint": "13",
      "pointHistory": [
        "1",
        "3",
        "2",
        "4",
        "1",
        "1",
        "1"
      ]
    },
    {
      "team": "大阪ヤンキース",
      "totalPoint": "0",
      "pointHistory": [
        "0",
        "0",
        "0",
        "0",
        "0",
        "0",
        "0"
      ]
    }
  ],
  "batter": [
    {
      "order": "1",
      "pos": "投手",
      "name": "渡辺(24)",
      "history": [
        "右2",
        "中安②",
        "",
        "一ゴ",
        "一ゴ",
        "左安",
        "",
        "",
        "",
        "",
        "",
        ""
      ],
      "打点": "2",
      "盗塁": "0",
      "盗失": "0",
      "得点": "1",
      "失策": "0",
      "美技": "0"
    },
    {
      "order": "2",
      "pos": "中堅手",
      "name": "藤原(44)",
      "history": [
        "投ゴ",
        "二ゴ①",
        "",
        "右安",
        "四球",
        "",
        "右安",
        "",
        "",
        "",
        "",
        ""
      ],
      "打点": "1",
      "盗塁": "0",
      "盗失": "0",
      "得点": "3",
      "失策": "0",
      "美技": "0"
    },
    {
      "order": "3",
      "pos": "二塁手",
      "name": "本田(3)",
      "history": [
        "二ゴ①",
        "遊ゴ",
        "",
        "捕飛",
        "左2",
        "",
        "中飛",
        "",
        "",
        "",
        "",
        ""
      ],
      "打点": "1",
      "盗塁": "0",
      "盗失": "0",
      "得点": "0",
      "失策": "0",
      "美技": "0"
    },
    {
      "order": "4",
      "pos": "一塁手",
      "name": "河合(25)",
      "history": [
        "左2",
        "",
        "四球",
        "三失",
        "遊安①",
        "",
        "三失",
        "",
        "",
        "",
        "",
        ""
      ],
      "打点": "1",
      "盗塁": "1",
      "盗失": "0",
      "得点": "2",
      "失策": "0",
      "美技": "0"
    },
    {
      "order": "5",
      "pos": "左翼手",
      "name": "三河(69)",
      "history": [
        "投ゴ",
        "",
        "中安",
        "四球",
        "三振",
        "",
        "二ゴ①",
        "",
        "",
        "",
        "",
        ""
      ],
      "打点": "1",
      "盗塁": "1",
      "盗失": "0",
      "得点": "2",
      "失策": "0",
      "美技": "0"
    },
    {
      "order": "6",
      "pos": "三塁手",
      "name": "平嶋(76)",
      "history": [
        "",
        "死球",
        "中安②",
        "右2②",
        "",
        "一飛",
        "二失",
        "",
        "",
        "",
        "",
        ""
      ],
      "打点": "4",
      "盗塁": "0",
      "盗失": "0",
      "得点": "1",
      "失策": "0",
      "美技": "0"
    },
    {
      "order": "7",
      "pos": "捕手",
      "name": "細野(15)",
      "history": [
        "",
        "投犠",
        "三振",
        "右安②",
        "",
        "投ゴ",
        "遊飛",
        "",
        "",
        "",
        "",
        ""
      ],
      "打点": "2",
      "盗塁": "0",
      "盗失": "0",
      "得点": "1",
      "失策": "0",
      "美技": "0"
    },
    {
      "order": "8",
      "pos": "右翼手",
      "name": "大野(53)",
      "history": [
        "",
        "三安",
        "三振",
        "三ゴ",
        "",
        "左2",
        "",
        "",
        "",
        "",
        "",
        ""
      ],
      "打点": "0",
      "盗塁": "0",
      "盗失": "0",
      "得点": "2",
      "失策": "0",
      "美技": "0"
    },
    {
      "order": "9",
      "pos": "遊撃手",
      "name": "宮野(2)",
      "history": [
        "",
        "投ゴ",
        "二飛",
        "",
        "左飛",
        "左安①",
        "",
        "",
        "",
        "",
        "",
        ""
      ],
      "打点": "1",
      "盗塁": "0",
      "盗失": "0",
      "得点": "1",
      "失策": "0",
      "美技": "0"
    }
  ],
  "pitcher": [
    {
      "name": "渡辺(24)",
      "イニング数": "4回0/3",
      "自責点": "0",
      "失点": "0",
      "三振": "5",
      "四球": "0",
      "死球": "0",
      "被安": "3",
      "被本": "",
      "投球数": "",
      "暴投": "",
      "勝敗": "勝"
    },
    {
      "name": "本田(3)",
      "イニング数": "2回0/3",
      "自責点": "0",
      "失点": "0",
      "三振": "1",
      "四球": "0",
      "死球": "0",
      "被安": "2",
      "被本": "",
      "投球数": "",
      "暴投": "",
      "勝敗": "-"
    },
    {
      "name": "河合(25)",
      "イニング数": "1回0/3",
      "自責点": "0",
      "失点": "0",
      "三振": "1",
      "四球": "0",
      "死球": "0",
      "被安": "0",
      "被本": "",
      "投球数": "",
      "暴投": "",
      "勝敗": "-"
    }
  ]
}